jsontableschema/VERSION
jsontableschema/__init__.py
jsontableschema/cli.py
jsontableschema/compat.py
jsontableschema/exceptions.py
jsontableschema/field.py
jsontableschema/helpers.py
jsontableschema/infer.py
jsontableschema/model.py
jsontableschema/pushpull.py
jsontableschema/schema.py
jsontableschema/storage.py
jsontableschema/table.py
jsontableschema/validate.py
jsontableschema/constraints/__init__.py
jsontableschema/constraints/enum.py
jsontableschema/constraints/maxLength.py
jsontableschema/constraints/maximum.py
jsontableschema/constraints/minLength.py
jsontableschema/constraints/minimum.py
jsontableschema/constraints/pattern.py
jsontableschema/constraints/required.py
jsontableschema/constraints/unique.py
jsontableschema/plugins/__init__.py
jsontableschema/schemas/geojson.json
jsontableschema/schemas/json-table-schema.json
jsontableschema/types/__init__.py
jsontableschema/types/any.py
jsontableschema/types/array.py
jsontableschema/types/base.py
jsontableschema/types/boolean.py
jsontableschema/types/date.py
jsontableschema/types/datetime.py
jsontableschema/types/duration.py
jsontableschema/types/geojson.py
jsontableschema/types/geopoint.py
jsontableschema/types/integer.py
jsontableschema/types/null.py
jsontableschema/types/number.py
jsontableschema/types/object.py
jsontableschema/types/string.py
jsontableschema/types/time.py
jsontableschema/types/year.py
jsontableschema/types/yearmonth.py
jsontableschema-0.10.1.dist-info/DESCRIPTION.rst
jsontableschema-0.10.1.dist-info/METADATA
jsontableschema-0.10.1.dist-info/RECORD
jsontableschema-0.10.1.dist-info/WHEEL
jsontableschema-0.10.1.dist-info/entry_points.txt
jsontableschema-0.10.1.dist-info/metadata.json
jsontableschema-0.10.1.dist-info/top_level.txt
