Metadata-Version: 2.0
Name: jsontableschema
Version: 0.10.1
Summary: A utility library for working with JSON Table Schema in Python
Home-page: https://github.com/frictionlessdata/jsontableschema-py
Author: Open Knowledge Foundation
Author-email: info@okfn.org
License: MIT
Keywords: frictionless data,open data,json schema,json table schema,data package,tabular data package
Platform: UNKNOWN
Classifier: Development Status :: 4 - Beta
Classifier: Environment :: Web Environment
Classifier: Intended Audience :: Developers
Classifier: License :: OSI Approved :: MIT License
Classifier: Operating System :: OS Independent
Classifier: Programming Language :: Python :: 2
Classifier: Programming Language :: Python :: 2.7
Classifier: Programming Language :: Python :: 3
Classifier: Programming Language :: Python :: 3.3
Classifier: Programming Language :: Python :: 3.4
Classifier: Programming Language :: Python :: 3.5
Classifier: Topic :: Internet :: WWW/HTTP :: Dynamic Content
Classifier: Topic :: Software Development :: Libraries :: Python Modules
Requires-Dist: click (>=3.3,<7.0)
Requires-Dist: future (>=0.15,<1.0)
Requires-Dist: isodate (>=0.5.4,<1.0)
Requires-Dist: jsonschema (>=2.5,<3.0)
Requires-Dist: python-dateutil (>=2.4,<3.0)
Requires-Dist: requests (>=2.5,<3.0)
Requires-Dist: rfc3986 (>=0.4,<1.0)
Requires-Dist: tabulator (>=1.0.0a5,<2.0)
Requires-Dist: unicodecsv (>=0.14,<1.0)
Provides-Extra: develop
Requires-Dist: pylama; extra == 'develop'
Requires-Dist: tox; extra == 'develop'
